{
  "data": [
    {
      "Instagram ID": "morinyeo",
      "조회수": 1766589,
      "조회수_한국어": "176만",
      "날짜": "2026-05-20",
      "카테고리": "뷰티/미용",
      "캡션": "📌3차 할인 ~5/25 자정까지입니다!!\n\n티 안나는 패치 지금 오픈!!!아직 품절 전입니다요!!🔥❤️\n\n이 여드름패치는,\n‘프란츠‘ 에서 나온 여드름 패치이구요🌿\n써보고 너무 좋아서 제가 할인가에 가져왔어요!\n\n1️⃣매우 얇아요🫰🏻\n\n보통 패치 두께는 (0.1~0.3mm)인데\n프란츠는 0.013mm로 다른 패치의\n10배는 얇은 두께에요 정말 얇아요!\n\n📌액티브만 진물 흡수를 위해 두꺼운 편인데 그럼에도 보통 패치들(0.3~0.1mm) 중에서도 0.1mm로 가장 얇은 편입니다!🫶🏻\n\n2️⃣초미세 공기 통로가 있어요 🌬️\n\n여드름은 산소가 차단되면,\n여드름도 더 커지고 균이 더 증식되는데\n이 패치는 공기 순환이 가능합니다\n\n3️⃣자외선이 차단돼요☀️\n\n색소침착의 가장 큰 원인인, 자외선!\n이 자외선 UV를 99% 차단합니다.\n영상에서 자외선 카메라로 찍은 모습 보셨죠?\n\n보통 여드름 패치는\n자외선 차단기능까지는 잘 없는데,\n\n프란츠에서 진짜 얇고 티 안 나는\n썬패치를 개발하다가 만들게 되신 거라\n자외선 차단도 가능한 제품입니다!\n\n서울대 출신 연구진들이\n서울대 유전공학연구소에서 개발한 제품으로\n기존의 여드름 패치의 단점 보완이 정말 많이 되었어요 :)\n\n원래 패치 1개당 (72매) 9000원에 판매되는데\n이번 할인가는 3개 (216매) + 전고객 사은품(12매)\n➡️이번 할인가는 이 모든 게 18500원..! 이랍니다🥹\n\n(거의 2+1 가격인셈이죠 ㅎㅎ)\n\n1set(2만원 이하)만 구매하셔도 무료 배송이구요!🚚📦\n\n바로 배송이라,\n11시 이전 주문건들은 바로 출고 됩니다!!\n개강, 입학 전에 받아보실 수 있을 거에요🤭💓\n\n제품관련한 구체적인 내용은\n가장 최근 게시물에서 보실 수 있구요..💓\n\n할인 기간은🗓️\n5/25 자정까지입니다!!",
      "썸네일": [
        {
          "url": "/assets/thumbnails/morinyeo.jpg",
          "localPath": "/home/runner/work/reels-leaderboard/reels-leaderboard/public/assets/thumbnails/morinyeo.jpg",
          "filename": "morinyeo.jpg",
          "width": 640,
          "height": 1136,
          "size": 54495,
          "type": "image/jpeg"
        }
      ],
      "영상URL": "https://www.instagram.com/p/DYjMB4LTDLc/"
    },
    {
      "Instagram ID": "r.no1",
      "조회수": 1311590,
      "조회수_한국어": "131만",
      "날짜": "2026-05-22",
      "카테고리": "패션",
      "캡션": "나도 몰랐음\n근데 알고 나서 진짜 달라 보이더라고요 \n잘 차려입어도,\n시선 처리 하나로 무드가 깨지곤 합니다\n격식 있는 자리에서 물이나 와인을 마실 때,\n눈을 위로 치켜뜨고 있진 않았는지 한번 체크해 보세요\n\n💾 저장해두면 다음 약속 전에 생각남\n📤 격식 있는 자리 앞둔 친구한테 보내줘요",
      "썸네일": [
        {
          "url": "/assets/thumbnails/r.no1.jpg",
          "localPath": "/home/runner/work/reels-leaderboard/reels-leaderboard/public/assets/thumbnails/r.no1.jpg",
          "filename": "r.no1.jpg",
          "width": 1080,
          "height": 1920,
          "size": 191828,
          "type": "image/jpeg"
        }
      ],
      "영상URL": "https://www.instagram.com/p/DYopIbhtV0f/"
    },
    {
      "Instagram ID": "fairy___hye",
      "조회수": 928757,
      "조회수_한국어": "92만",
      "날짜": "2026-05-18",
      "카테고리": "헬스케어",
      "캡션": "믿어도 되는 속설인지 아닌지는\n성별 나오면 알려드릴게요..💭\n\n(엄마들 🌶️ 이거 사실인가요 👀..?)\n\n#말띠맘 #둘째맘 #임신10주 #성별확인",
      "썸네일": [
        {
          "url": "/assets/thumbnails/fairy___hye.jpg",
          "localPath": "/home/runner/work/reels-leaderboard/reels-leaderboard/public/assets/thumbnails/fairy___hye.jpg",
          "filename": "fairy___hye.jpg",
          "width": 1080,
          "height": 1920,
          "size": 204115,
          "type": "image/jpeg"
        }
      ],
      "영상URL": "https://www.instagram.com/p/DYeabdKp1dc/"
    },
    {
      "Instagram ID": "bbombrunch",
      "조회수": 675294,
      "조회수_한국어": "67만",
      "날짜": "2026-05-20",
      "카테고리": "요리",
      "캡션": "겁도 없이 통목살 6덩이를 집어왔는데\n막상 해먹어 보니까\n금방 먹어치울 것 같은 맛🙂\n\n소금, 후추만 살짝 하고\n마요네즈 얇게 바른 뒤\n전분가루까지 묻혀 구워봤는데\n겉면이 진짜 제대로예요.\n\n바삭하게 익은 고기에\n햇양파 듬뿍 넣어 만든 소스까지 올려주면\n이게 밥반찬인지 스테이크인지\n조금 헷갈릴 정도🙂\n\n통목살이라 두툼한데도\n안은 촉촉하고 육즙은 살아있고,\n한입 크기로 썰어 먹다 보면\n진짜 끝도 없이 들어갑니다.\n\n요즘 맛있는 햇양파 양껏 넣고\n같이 볶아 먹으면 단맛이 확 올라와서\n생각보다 훨씬 잘 어울리더라고요🙂\n\n🥩 통목살 양파스테이크\n\n✔ 통목살은 칼집 내어 밑간\n소금, 후추\n마요네즈 얇게 코팅\n감자전분 살짝 묻히기\n\n✔ 소스\n간장 3큰술\n굴소스 2큰술\n미림 2큰술\n다진마늘 1큰술\n알룰로스 1큰술\n식초 1큰술\n\n목살은 올리브유 넉넉하게 둘러\n굴려가며 골고루 구워주세요🙂\n\n팬에서 잠깐 꺼내 레스팅 해둔 뒤\n고기 구운 팬 그대로 소스를 만들어줍니다.\n\n썰어둔 햇양파 1개 넣고\n감자전분 2꼬집도 같이 넣어\n소스가 맛있게 엉겨붙을 정도까지 볶아주세요.\n\n마지막으로 목살 위에 소스 듬뿍 올리고\n한입 크기로 썰어 맛있게 먹기🙂\n\n#통목살 #목살스테이크 #집밥레시피 \n#햇양파 #양파소스",
      "썸네일": [
        {
          "url": "/assets/thumbnails/bbombrunch.jpg",
          "localPath": "/home/runner/work/reels-leaderboard/reels-leaderboard/public/assets/thumbnails/bbombrunch.jpg",
          "filename": "bbombrunch.jpg",
          "width": 1080,
          "height": 1917,
          "size": 160945,
          "type": "image/jpeg"
        }
      ],
      "영상URL": "https://www.instagram.com/p/DYjweGoBI-y/"
    },
    {
      "Instagram ID": "eunbin_dung",
      "조회수": 582626,
      "조회수_한국어": "58만",
      "날짜": "2026-05-22",
      "카테고리": "교육/정보성",
      "캡션": "엄마한테 등짝 맞으면서 알려드리는 꿀팁..😂\n집 안 모기, 90%가 현관문으로 들어온대요.\n\n저도 유치원 교사 하면서\n모기, 먹파리 등 온갖 벌레 물리고 나서야 \n스프레이의 중요성을 알게됐거든요😖\n\n향패치는 기존에 갖고있던 향이 \n날아가면 효과가 떨어져요\n(천연 식물 오일이라 당연한 거❗️)\n\n그래서 거기에 스프레이를 뿌려\n외부에서도, 현관문에도 활용해 보세요~!\n(이미 사용해서 너덜거리면 자석으로 고정시키기 추천~!)\n\n➡️ 무조건 100% 못 들어오게는 아니더라도\n조금이라도 덜 물릴 수 있다면 저는\n어떻게든 활용하고 싶거든요😭\n(먹파리 물려본 자의 서러움..)\n\n📌 동국제약 모기 퇴치 패키지📌\n\n➡️ 궁금해 하실 내용 모두!\n프로필 링크 구매 안내서에 정리해 놨어요❤️\n\n📍[벅스케이프 스프레이 3종]\n\n✔️ 미스트 포 베이비\n➡️신생아·임산부도 사용 가능 (의사 확인 후)\n\n✔️ 스프레이 아웃도어\n➡️이카리딘 15%, 살인 진드기·먹파리까지\n\n✔️ 에프터 바이트\n➡️물린 후 쿨링+소독까지\n\n📍[마데카 썸머 패치 3종]\n\n✔️ 향패치\n➡️국내 공장 생산\n➡️화학물질 확인 결과 적합 O\n➡️피부 부착 X / 옷 부착 O\n\n✔️ BIG 패치\n➡️압도적 사이즈로 지속력 UP\n➡️프리미엄 부직포 원단으로 지속 효과 UP\n➡️피부 부착 X / 옷 부착 O\n\n✔️ 겔패치\n➡️동국제약 테카 성분, 물린 후 빠른 진정\n\n📍 모기 퇴치 패키지는 일요일 마감됩니다🫶🫡",
      "썸네일": [
        {
          "url": "/assets/thumbnails/eunbin_dung.jpg",
          "localPath": "/home/runner/work/reels-leaderboard/reels-leaderboard/public/assets/thumbnails/eunbin_dung.jpg",
          "filename": "eunbin_dung.jpg",
          "width": 640,
          "height": 1136,
          "size": 57282,
          "type": "image/jpeg"
        }
      ],
      "영상URL": "https://www.instagram.com/p/DYoy_isuVvl/"
    },
    {
      "Instagram ID": "black_jinjuu",
      "조회수": 569518,
      "조회수_한국어": "56만",
      "날짜": "2026-05-22",
      "카테고리": "교육/정보성",
      "캡션": "여러분은 어떻게 계산해요?😂😂\n\n#수학",
      "썸네일": [
        {
          "url": "/assets/thumbnails/black_jinjuu.jpg",
          "localPath": "/home/runner/work/reels-leaderboard/reels-leaderboard/public/assets/thumbnails/black_jinjuu.jpg",
          "filename": "black_jinjuu.jpg",
          "width": 640,
          "height": 1136,
          "size": 41687,
          "type": "image/jpeg"
        }
      ],
      "영상URL": "https://www.instagram.com/p/DYn5GhsSPmb/"
    },
    {
      "Instagram ID": "2wins_bubu",
      "조회수": 530605,
      "조회수_한국어": "53만",
      "날짜": "2026-05-20",
      "카테고리": "퍼스널",
      "캡션": "누가누가 잘하나하",
      "썸네일": [
        {
          "url": "/assets/thumbnails/2wins_bubu.jpg",
          "localPath": "/home/runner/work/reels-leaderboard/reels-leaderboard/public/assets/thumbnails/2wins_bubu.jpg",
          "filename": "2wins_bubu.jpg",
          "width": 640,
          "height": 1136,
          "size": 50400,
          "type": "image/jpeg"
        }
      ],
      "영상URL": "https://www.instagram.com/p/DYjeDezJrYH/"
    },
    {
      "Instagram ID": "my_youth_nae_youth",
      "조회수": 500237,
      "조회수_한국어": "50만",
      "날짜": "2026-05-19",
      "카테고리": "비즈니스",
      "캡션": "💡 1초 만에 ’ㅅ‘ 발음 좋아지는 꿀팁 요약\n\n1️⃣ 으 발음으로 소리내기 \n2️⃣ 기분 좋게😊 미소 지으며 치아 사이에 종이 한 장 틈만 열어주기\n3️⃣ 타이어에서 바람 빠지듯 스~~ 차가운 공기 먼저 뱉어보기💨\n4️⃣ 턱을 가볍게 내려주기 \n\n지금 바로 저장해두고, \n거울을 보며 ’사슴 선생님, 사랑해요‘를 연습해 보세요!\n\n어떤 발음이 가장 안 되시나요? \n댓글로 남겨주시면 다음 영상에서 다뤄볼게요. 👇\n\n#내유스 #스피치 #발표 #보이스 #목소리",
      "썸네일": [
        {
          "url": "/assets/thumbnails/my_youth_nae_youth.jpg",
          "localPath": "/home/runner/work/reels-leaderboard/reels-leaderboard/public/assets/thumbnails/my_youth_nae_youth.jpg",
          "filename": "my_youth_nae_youth.jpg",
          "width": 640,
          "height": 1136,
          "size": 81790,
          "type": "image/jpeg"
        }
      ],
      "영상URL": "https://www.instagram.com/p/DYfHcyUPRQ-/"
    },
    {
      "Instagram ID": "zintol_",
      "조회수": 491770,
      "조회수_한국어": "49만",
      "날짜": "2026-05-18",
      "카테고리": "퍼스널",
      "캡션": "불닭냉면을 모티브로 만든 마라샹궈냉면육수 먹빠앙..👀\n이 조합... 과연 괴식일까 미식일까?\n\n#먹방 #도전먹방 #mukbang #asmr #foodie",
      "썸네일": [
        {
          "url": "/assets/thumbnails/zintol_.jpg",
          "localPath": "/home/runner/work/reels-leaderboard/reels-leaderboard/public/assets/thumbnails/zintol_.jpg",
          "filename": "zintol_.jpg",
          "width": 640,
          "height": 1136,
          "size": 73987,
          "type": "image/jpeg"
        }
      ],
      "영상URL": "https://www.instagram.com/p/DYex-8SzgWu/"
    },
    {
      "Instagram ID": "emily.at_home",
      "조회수": 489607,
      "조회수_한국어": "48만",
      "날짜": "2026-05-17",
      "카테고리": "요리",
      "캡션": "다른 곳도 아닌 계단에서 굴러 넘어져\n아이가 이만하길 너무 다행이다 싶지만\n절뚝거리는 아이 모습에\n매일 두세 번 상처에 약 발라주는 엄마 마음은 참 속상하네요.😭\n\n근데 정작 아이는\n자기 아픈 것보다\n친구 혼날 걱정을 먼저 하더라고요.\n\n아이 이야기를 듣고\n엄마인 저는 마음이 참 복잡했어요.\n\n남을 먼저 생각하는 마음은 참 예쁜데,\n정작 자기 아픔은 숨기는 아이가 될까 봐요…\n\n이럴 때 엄마는\n어떤 말을 해줘야 할까요?🥹",
      "썸네일": [
        {
          "url": "/assets/thumbnails/emily.at_home.jpg",
          "localPath": "/home/runner/work/reels-leaderboard/reels-leaderboard/public/assets/thumbnails/emily.at_home.jpg",
          "filename": "emily.at_home.jpg",
          "width": 640,
          "height": 1136,
          "size": 53004,
          "type": "image/jpeg"
        }
      ],
      "영상URL": "https://www.instagram.com/p/DYbe8ENSy05/"
    },
    {
      "Instagram ID": "norang_minju",
      "조회수": 454206,
      "조회수_한국어": "45만",
      "날짜": "2026-05-19",
      "카테고리": "비즈니스",
      "캡션": "새벽 한 시,두 시, 세 시..\n잠이 들었다가 문득 깼는데\n그는 집에 오지 않았습니다\n오늘 새벽 일찍 나갔는데..\n왜 안 들어오지?\n오다가 무슨 사고라도??\n아.. 이인간이 바람이 났구나!!!\n그게 아니면 매일 이리 늦게 들어올 이유가 없으니깐요\n그 새벽에 쿵쾅쿵쾅 떨리는 가슴을 부여 잡고 가게로 갑니다\n인적드문 거리,불 꺼진 가게들..\n조용히 빛이 흘러 나오는 우리 가게서 그는 여전히\n일을 하고 있습니다\n하루종일 서서 일했을텐데..\n분명 제대로 밥도 못 먹었을텐데..\n이 미친년아!!!!!\n의심할걸 의심해라\n내 자신이 너무나 추잡스럽게 한심해서 그리고 미안해서\n대성통곡을 합니다\n저는 그가 제발 쉽게,편하게 살았음 좋겠습니다\n제발🙏\n\n#자영업자 #자영업자일상\n#노비루\n#셰프아빠의만능맛간장",
      "썸네일": [
        {
          "url": "/assets/thumbnails/norang_minju.jpg",
          "localPath": "/home/runner/work/reels-leaderboard/reels-leaderboard/public/assets/thumbnails/norang_minju.jpg",
          "filename": "norang_minju.jpg",
          "width": 1080,
          "height": 1917,
          "size": 178668,
          "type": "image/jpeg"
        }
      ],
      "영상URL": "https://www.instagram.com/p/DYhXCCKzYvo/"
    },
    {
      "Instagram ID": "hyowithsweet",
      "조회수": 452013,
      "조회수_한국어": "45만",
      "날짜": "2026-05-22",
      "카테고리": "요리",
      "캡션": "섞기만 하면 끝나는데\n사먹는 것보다 맛있는 바스크치즈케이크 !!!!\n제가 몇번이나 테스트해서 정착한 비율이에요 ㅎㅎ\n\n너무 묽지도 너무 꾸덕하지도 않아서\n혀에 촥 감기는 텍스쳐가 예술이랍니다 👍🏻👍🏻👍🏻\n만들어 드시고 맛있으셨다면 후기 남겨주세요 히히… ♥️\n그러면 앞으로도 더더 맛있는 레시피 가져오겠씁니다 !!!!\n\n🧀 바스크치즈케이크 레시피 🧀\n(1호 원형틀 1개 기준)\n\n* 크림치즈 430g\n* 설탕 125g\n* 달걀 156g\n* 동물성생크림 280g\n* 옥수수전분 15g\n* 타피오카전분 15g\n* 바닐라익스트랙 혹은 바닐라빈 (없어도 맛있어서 전 뺐어요!)\n\n(사용한 제품은 프로필 링크에서 확인해주세요♥️)",
      "썸네일": [
        {
          "url": "/assets/thumbnails/hyowithsweet.jpg",
          "localPath": "/home/runner/work/reels-leaderboard/reels-leaderboard/public/assets/thumbnails/hyowithsweet.jpg",
          "filename": "hyowithsweet.jpg",
          "width": 1080,
          "height": 1920,
          "size": 124879,
          "type": "image/jpeg"
        }
      ],
      "영상URL": "https://www.instagram.com/p/DYolcOxRJLP/"
    },
    {
      "Instagram ID": "tuntun2mom",
      "조회수": 437240,
      "조회수_한국어": "43만",
      "날짜": "2026-05-23",
      "카테고리": "일상",
      "캡션": "아 놔 계획대로 안대네 🤦‍♀️💥\n둘째 계획중인 사람에게 전달!!! ✈️\n\n#40대맘 #친정아빠 #팩폭 #육아시트콤 # 울산아지매",
      "썸네일": [
        {
          "url": "/assets/thumbnails/tuntun2mom.jpg",
          "localPath": "/home/runner/work/reels-leaderboard/reels-leaderboard/public/assets/thumbnails/tuntun2mom.jpg",
          "filename": "tuntun2mom.jpg",
          "width": 640,
          "height": 1136,
          "size": 53156,
          "type": "image/jpeg"
        }
      ],
      "영상URL": "https://www.instagram.com/p/DYrM6ilpkqz/"
    },
    {
      "Instagram ID": "mama_zones",
      "조회수": 360665,
      "조회수_한국어": "36만",
      "날짜": "2026-05-22",
      "카테고리": "살림/육아",
      "캡션": "🪳이 벌레가 나온다고?\n댓🙌 벌레 영상속 제품 링크를 \n보내드려요\n\n✅좀벌레 트랩 영상 올렸을 때\n“몇 달 뒤엔 어떻게 됐어요?”\n문의가 정말 많았거든요😳\n\n그래서 이전에 찍었던 설치 영상이랑\n얼마나전에 올린 몇 개월 뒤 실제 \n효과 영상까지 같이 묶어봤어요.\n\n안 보인다고 없는 게 아니었네요…\n청소하다 발견하고 진짜 식겁했습니다😱\n\n이 정도로 잡혀있을 줄은 몰랐는데\n효과는 제대로 본 것 같아요👍\n\n🔺영상 속 제품은 프로필 링크 하단에서도\n보실 수 있으세요\n\n오늘도 마마존스와\n즐거운 살림하세요\n\n#살림템 #벌레퇴치 #벌레 #살림꿀템 #살림템추천",
      "썸네일": [
        {
          "url": "/assets/thumbnails/mama_zones.jpg",
          "localPath": "/home/runner/work/reels-leaderboard/reels-leaderboard/public/assets/thumbnails/mama_zones.jpg",
          "filename": "mama_zones.jpg",
          "width": 1080,
          "height": 1920,
          "size": 218048,
          "type": "image/jpeg"
        }
      ],
      "영상URL": "https://www.instagram.com/p/DYo5Yv8S83Z/"
    },
    {
      "Instagram ID": "shine_yaksa",
      "조회수": 328924,
      "조회수_한국어": "32만",
      "날짜": "2026-05-20",
      "카테고리": "헬스케어",
      "캡션": "▶️공유) 약사가 암예방 위해 먹는 영양제 TOP5\n\n암은 치료보다\n예방이 훨씬 중요합니다\n\n약사가\n암 예방을 위해 챙기는\n영양제 5가지 알려드릴게요\n\n❌ 꼭 기억하세요\n암을 치료하는 영양제는 없습니다\n그렇게 광고하는건 일단 거르세요\n\n5위 오메가3\n: 암은 만성 염증과 연결됩니다\n오메가3는 염증을 낮추고\n암세포가 자라기 쉬운 환경을 줄여주는\n기본 영양소예요\n\n4위 비타민C\n: 활성산소가 많아질수록\n세포 손상이 심해집니다\n비타민C는 산화 스트레스를 줄이고\n면역 환경 관리에 도움됩니다\n\n3위 셀레늄\n: 암은 결국 DNA 손상에서 시작됩니다\n셀레늄은 손상된 세포를 보호하고\n비정상 세포가 커지는 걸 막는 데 도움됩니다\n항암 보조 연구 데이터도 많아요\n\n2위 비타민D\n: 암 예방 연구가 가장 많은 비타민 중 하나예요\n면역세포인 NK세포, T세포 활성에 관여해서\n몸이 암세포를 감시하는 기능을 도와줍니다\n\n1위 커큐민\n: 염증, 산화 스트레스, 암세포 신호를\n한 번에 관리하는 성분입니다\n특히 위암, 대장암 같은\n소화기계 암 관련 데이터가 많고\n암 가족력이 있다면 미리 관리하는 분들도 많아요\n\n암은 어느 날 갑자기 생기는 게 아니라\n염증과 세포 손상이\n오랫동안 반복되면서 시작됩니다\n\n📍이 영상 저장해두고\n부모님, 가족 건강을 위해 꼭 공유해주세요\n\n더 많은 건강 정보는 @shine_yaksa 팔로우\n\n#암예방 #염증",
      "썸네일": [
        {
          "url": "/assets/thumbnails/shine_yaksa.jpg",
          "localPath": "/home/runner/work/reels-leaderboard/reels-leaderboard/public/assets/thumbnails/shine_yaksa.jpg",
          "filename": "shine_yaksa.jpg",
          "width": 640,
          "height": 1136,
          "size": 45231,
          "type": "image/jpeg"
        }
      ],
      "영상URL": "https://www.instagram.com/p/DYkBQzuvA3Z/"
    }
  ],
  "lastUpdated": "2026-05-29T02:31:58.783Z",
  "weekStart": "2026-05-25",
  "generatedAt": "2026-05-29T02:31:58.783Z"
}